{"id":"mdzz_in_out","name":"mdzz_in_out","status":"STOPPED","esperHAEnabled":false,"enableErrorHandler":true,"topologySupervisors":[],"versionNumber":3,"parentVersionNumber":3,"description":"","customJarName":"","originalCustomJarName":"","customFileNames":"http.json","sessionId":"656ECACF059B8B8C9951EF66F72C94F7","isReplayAlter":false,"engine":"spark","scheduling":null,"config":{"batchDuration":"1000","yarnUser":"hdfs","logLevel":"TRACE","keyTabSelectOption":"specifyKeyTabFilePath","keyTabFilePath":"","downloadKeytabFileLocation":"","zkKeyTabFileLocation":"","executorCores":"2","executorMemory":"512","receiverRateLimiter":"none","receiverMaxRate":"","enableBackPressure":"","enableCheckPoint":"false","checkPointDirectory":"/","eventLogEnabled":"false","eventLogDirectory":"/","poolNname":"FIFO","deploymentMode":"local","driverCores":"1","driverPermGenSize":"256","driverMemory":"512","taskMaxFailures":"4","yarnAmCores":"1","yarnAmMemory":"512","dynamicAllocationEnabled":"false","initialExecutors":"0","maxExecutors":"-1","executorInstances":"1","yarnQueue":"default","connectionName":"","appCores":"2","engine":"spark","typeOfApplication":"structuredstreaming","autoInspection":false,"clouderaLineage":false,"isConnectionMissing":false,"isDirty":false},"channels":[{"coordinates":[10,10],"className":"com.streamanalytix.spark.ss.receiver.SparkSSReceiver","label":"RabbitMQ","inputDStreamType":"na","emitStreamIds":[{"emitStreamId":"defaultStream","outputFields":["tracemessage","streamIds"],"applyFilter":false,"filterCriteria":[],"componentId":"RabbitMQ_21627"},{"emitStreamId":"saxErrorStream","outputFields":["tracemessage","streamIds"],"applyFilter":false,"filterCriteria":[],"componentId":"deadLaterChannel"}],"appType":"structuredstreaming","messageTypeId":"tracemessage","name":"RabbitMQChannel_859512","id":"rabbitmq-channel","schemaIdentifier":"com.streamanalytix.engine.core.scheme.util.DefaultSchemaIdentifier","outputDStreamType":"plain","config":{"queueDurable":"true","exchangeAutoDelete":"false","exchangeType":"direct","queueAutoDelete":"false","exchangeDurable":"true","channelPlugin":"com.streamanalytix.spark.ss.receiver.SparkSource","sourceProvider":"com.streamanalytix.spark.ss.receiver.provider.SourceProvider","queueName":"mdzz_in","connectionId":"b3f72276-0e50-476e-888f-3c2d609f4ae5","sourcePlugin":"com.streamanalytix.spark.ss.receiver.source.RmqSSSource","exchangeName":"mdzz_in","queueExclusive":"false","connectionName":"Default","routingKey":"mdzz_in","connectionConfig":{"connectionName":"Default","channelPlugin":"com.streamanalytix.spark.ss.receiver.SparkSource"},"operatorType":"receiver","saxInspect":{"datasetIds":{"inputdatasetId":[],"outputdatasetId":["RabbitMQChannel_859512"]},"referenceSchemaId":{"inputSchemaId":[],"outputSchemaId":["RabbitMQChannel_859512"]},"rowCount":100,"triggerTime":"3 seconds","samplingMethod":"topN","typeOfSchemaDetection":"fileUpload","autoInspectHdfsFilePath":"456.csv","header":true,"detectSchema":false},"subsystemName":"mdzz_in_out","parentTag":"/","parserType":"json","delimiter":",","expfldlst":"","mvelfnclist":[],"sourceHeader":false},"type":"channel","messageTypes":["RabbitMQChannel_859512"],"channelType":"single","configured":true,"groupings":[],"errorConfig":{"partitions":"","connectionName":"Default","connectionId":"b3f72276-0e50-476e-888f-3c2d609f4ae5","componentType":"rabbitmq","errorLogTarget":"rabbitmq","replicationFactor":"","isErrorHandlingRequired":true},"datamodel":[]}],"processors":[{"coordinates":[90,10],"className":"com.streamanalytix.spark.ss.processor.StructuredStreamingProcessor","label":"RabbitMQ","inputDStreamType":"both","type":"emitter","emitStreamIds":[{"emitStreamId":"saxErrorStream","outputFields":["tracemessage","streamIds"],"applyFilter":false,"filterCriteria":[],"componentId":"deadLaterChannel"}],"groupings":[{"type":"shuffle","componentId":"RabbitMQChannel_859512","groupFields":[],"streamId":"defaultStream"}],"appType":"structuredstreaming","messageTypeId":"tracemessage","name":"RabbitMQ_21627","id":"rabbitmq-emitter","outputDStreamType":"both","config":{"queueDurable":"true","message-ttl":"","stompUrl":"","exchangeType":"direct","queueAutoDelete":"false","virtualHost":"","exchangeDurable":"true","delimiter":"","queueExclusive":"false","x-dead-letter-queue":"","outputFormat":"json","x-dead-letter-routing-key":"","isEnableTtlAltered":false,"enable-ttl":"false","exchangeAutoDelete":"false","trigger":false,"outputFields":["age","id","name","salary"],"x-dead-letter-exchange":"","queueName":"mdzz_out","checkpointLocation":"","checkpointConnectionId":"","connectionId":"b3f72276-0e50-476e-888f-3c2d609f4ae5","outputmode":"append","exchangeName":"mdzz_out","connectionName":"Default","batchSize":"1","checkpointConnectionType":"hdfs","executorPlugin":"com.streamanalytix.spark.ss.helper.RMQEmitterHelper","isBatchEnable":"false","routingKey":"mdzz_out","connectionConfig":{"connectionName":"Default"},"operatorType":"processor","saxInspect":{"datasetIds":{"inputdatasetId":["RabbitMQChannel_859512"],"outputdatasetId":["RabbitMQ_21627"]},"referenceSchemaId":{"inputSchemaId":["RabbitMQChannel_859512"],"outputSchemaId":["RabbitMQChannel_859512"]}},"subsystemName":"mdzz_in_out","parentTag":"/","processingTimeUnit":"seconds","processingTime":"","expfldlst":"","mvelfnclist":[]},"subtype":"","messageTypes":["RabbitMQChannel_859512"],"channelType":"single","configured":true,"errorConfig":{"partitions":"","connectionName":"Default","connectionId":"b3f72276-0e50-476e-888f-3c2d609f4ae5","componentType":"rabbitmq","errorLogTarget":"rabbitmq","replicationFactor":"","isErrorHandlingRequired":true}}],"templateName":"","structure":"pipeline","alert":{"added":[],"updated":[],"deleted":[]},"connections":["b3f72276-0e50-476e-888f-3c2d609f4ae5","b3f72276-0e50-476e-888f-3c2d609f4ae5"],"autoInspectSchema":{"RabbitMQChannel_859512":[{"name":"age","alias":"age","dataType":"java.lang.Long","dateFormat":"yyyy-MM-dd HH:mm:ss","inputDateFormat":"yyyy-MM-dd HH:mm:ss","outputDateFormat":"yyyy-MM-dd HH:mm:ss","stringToDate":false,"isInputField":"Y","isTimestampField":"N","selected":true},{"name":"id","alias":"id","dataType":"java.lang.Long","dateFormat":"yyyy-MM-dd HH:mm:ss","inputDateFormat":"yyyy-MM-dd HH:mm:ss","outputDateFormat":"yyyy-MM-dd HH:mm:ss","stringToDate":false,"isInputField":"Y","isTimestampField":"N","selected":true},{"name":"name","alias":"name","dataType":"java.lang.String","dateFormat":"yyyy-MM-dd HH:mm:ss","inputDateFormat":"yyyy-MM-dd HH:mm:ss","outputDateFormat":"yyyy-MM-dd","stringToDate":false,"isInputField":"Y","isTimestampField":"N","selected":true},{"name":"salary","alias":"salary","dataType":"java.lang.Double","dateFormat":"yyyy-MM-dd HH:mm:ss","inputDateFormat":"yyyy-MM-dd HH:mm:ss","outputDateFormat":"yyyy-MM-dd HH:mm:ss","stringToDate":false,"isInputField":"Y","isTimestampField":"N","selected":true}]},"displayColumnsMap":{"RabbitMQChannel_859512":{"RabbitMQChannel_859512":{"allCols":["age","id","name","salary"],"displayCols":["id","name","age","salary"],"types":{"age":"java.lang.Long","id":"java.lang.Long","name":"java.lang.String","salary":"java.lang.Double"},"uniqueValues":{"name":1,"id":1,"salary":1,"age":1}}},"RabbitMQ_21627":{"RabbitMQChannel_859512":{"allCols":["age","id","name","salary"],"displayCols":["id","name","age","salary"],"types":{"age":"java.lang.Long","id":"java.lang.Long","name":"java.lang.String","salary":"java.lang.Double"},"uniqueValues":{"name":1,"id":1,"salary":1,"age":1}}}},"customJarBeforeModification":"","httpSessionId":"656ECACF059B8B8C9951EF66F72C94F7","inspectType":"local","subsystemName":"mdzz_in_out","tenantId":"7","tempPipelineName":"Pipeline_1572836249101"}